password_system/__init__.py
password_system-1.0.dist-info/METADATA
password_system-1.0.dist-info/RECORD
password_system-1.0.dist-info/WHEEL
password_system-1.0.dist-info/top_level.txt
