Metadata-Version: 2.1
Name: password-system
Version: 1.0
Summary: A complete password system.
Home-page: https://github.com/jamesg31/Password-System
Author: jamesg31
Author-email: jamie.gardner25@gmail.com
License: UNKNOWN
Platform: UNKNOWN
Classifier: Programming Language :: Python :: 3
Classifier: License :: OSI Approved :: MIT License
Classifier: Operating System :: OS Independent
